{
    "version": 3,
    "configurePresets": [
        {
            "name": "default",
            "hidden": true,
            "generator": "Ninja",
            "binaryDir": "${sourceDir}/build/${presetName}",
            "toolchainFile": "${sourceDir}/cmake/gcc-arm-none-eabi.cmake",
            "cacheVariables": {
                "CMAKE_BUILD_TYPE": "Release",
                "ENABLE_LTO": false,
                "ENABLE_FMRADIO": false,
                "ENABLE_UART": true,
                "ENABLE_USB": false,
                "ENABLE_NOAA": false,
                "ENABLE_VOICE": false,
                "ENABLE_VOX": false,
                "ENABLE_ALARM": false,
                "ENABLE_TX1750": true,
                "ENABLE_PWRON_PASSWORD": false,
                "ENABLE_DTMF_CALLING": false,
                "ENABLE_FLASHLIGHT": true,
                "ENABLE_SPECTRUM": true,
                "ENABLE_FR_BAND": false,
                "ENABLE_KO_BAND": false,
                "ENABLE_BIG_FREQ": true,
                "ENABLE_CUSTOM_MENU_LAYOUT": true,
                "ENABLE_KEEP_MEM_NAME": true,
                "ENABLE_WIDE_RX": true,
                "ENABLE_TX_WHEN_AM": false,
                "ENABLE_F_CAL_MENU": false,
                "ENABLE_CTCSS_TAIL_PHASE_SHIFT": false,
                "ENABLE_BOOT_BEEPS": false,
                "ENABLE_SHOW_CHARGE_LEVEL": false,
                "ENABLE_REVERSE_BAT_SYMBOL": false,
                "ENABLE_NO_CODE_SCAN_TIMEOUT": true,
                "ENABLE_SQUELCH_MORE_SENSITIVE": true,
                "ENABLE_FASTER_CHANNEL_SCAN": true,
                "ENABLE_RSSI_BAR": true,
                "ENABLE_AUDIO_BAR": true,
                "ENABLE_COPY_CHAN_TO_VFO": true,
                "ENABLE_REDUCE_LOW_MID_TX_POWER": false,
                "ENABLE_BYP_RAW_DEMODULATORS": false,
                "ENABLE_BLMIN_TMP_OFF": false,
                "ENABLE_SCAN_RANGES": true,
                "ENABLE_REGA": false,
                "ENABLE_EXTRA_UART_CMD": false,
                "ENABLE_FEAT_ROBZYL": true,
                "ENABLE_FEAT_ROBZYL_SCREENSHOT": false,
                "ENABLE_FEAT_ROBZYL_SPECTRUM": true,
                "ENABLE_FEAT_ROBZYL_RX_TX_TIMER": true,
                "ENABLE_FEAT_ROBZYL_CHARGING_C": false,
                "ENABLE_FEAT_ROBZYL_SLEEP": true,
                "ENABLE_FEAT_ROBZYL_RESUME_STATE": true,
                "ENABLE_FEAT_ROBZYL_NARROWER": true,
                "ENABLE_FEAT_ROBZYL_INV": true,
                "ENABLE_FEAT_ROBZYL_CTR": true,
                "ENABLE_FEAT_ROBZYL_RESCUE_OPS": false,
                "ENABLE_FEAT_ROBZYL_VOL": false,
                "ENABLE_FEAT_ROBZYL_AUDIO": false,
                "ENABLE_FEAT_ROBZYL_RESET_VFO": true,
                "ENABLE_FEAT_ROBZYL_PMR": false,
                "ENABLE_FEAT_ROBZYL_GMRS_FRS_MURS": false,
                "ENABLE_FEAT_ROBZYL_CA": true,
                "ENABLE_FEAT_ROBZYL_DEBUG": false,
                "ENABLE_AGC_SHOW_DATA": false,
                "ENABLE_UART_RW_BK_REGS": false,
                "ENABLE_SWD": false,
                "VERSION_STRING_1": "v0.22",
                "VERSION_STRING_2": "V1.0"
            }
        },
       
        {
            "name": "France",
            "inherits": "default",
            "cacheVariables": {
                "ENABLE_FR_BAND": true,
                "EDITION_STRING": "France",
                "TARGET": "ROBZYL.K1.France"
            }
        },
        {
            "name": "Kolyan",
            "inherits": "default",
            "cacheVariables": {
                "ENABLE_KO_BAND": true,
                "EDITION_STRING": "Kolyan",
                "TARGET": "ROBZYL.K1.Kolyan"
            }
        },
        {
            "name": "Russia",
            "inherits": "default",
            "cacheVariables": {
                "ENABLE_RU_BAND": true,
                "EDITION_STRING": "Russia",
                "TARGET": "ROBZYL.K1.Russia"
            }
        },
        {
            "name": "Poland",
            "inherits": "default",
            "cacheVariables": {
                "ENABLE_PL_BAND": true,
                "EDITION_STRING": "Poland",
                "TARGET": "ROBZYL.K1.Poland"
            }
        }
    ],
    "buildPresets": [
        {
            "name": "France",
            "configurePreset": "France"
        },
        {
            "name": "Kolyan",
            "configurePreset": "Kolyan"
        },
        {
            "name": "Russia",
            "configurePreset": "Russia"
        },
        {
            "name": "Poland",
            "configurePreset": "Poland"
        }
    ]
}